add_arb_metadata.py
add_descriptions_intelligently.py
arb_metadata_tools-1.1.0.dist-info/licenses/LICENSE
arb_metadata_tools-1.1.0.dist-info/METADATA
arb_metadata_tools-1.1.0.dist-info/WHEEL
arb_metadata_tools-1.1.0.dist-info/entry_points.txt
arb_metadata_tools-1.1.0.dist-info/top_level.txt
arb_metadata_tools-1.1.0.dist-info/RECORD
