Metadata-Version: 2.4
Name: arb-metadata-tools
Version: 1.1.0
Summary: Automatically manage metadata in ARB (Application Resource Bundle) localization files for Flutter, Angular, Chrome extensions, and more
Home-page: https://github.com/JehadurRE/arb-metadata-tools
Author: Md. Jehadur Rahman Emran
Author-email: "Md. Jehadur Rahman Emran" <emran.jehadur@gmail.com>
Maintainer-email: "Md. Jehadur Rahman Emran" <emran.jehadur@gmail.com>
License: MIT
Project-URL: Homepage, https://github.com/JehadurRE/arb-metadata-tools
Project-URL: Documentation, https://github.com/JehadurRE/arb-metadata-tools#readme
Project-URL: Repository, https://github.com/JehadurRE/arb-metadata-tools
Project-URL: Bug Tracker, https://github.com/JehadurRE/arb-metadata-tools/issues
Project-URL: Portfolio, https://portfolio.jehadurre.icu
Keywords: arb,localization,i18n,l10n,internationalization,metadata,automation,flutter,angular,chrome-extension
Classifier: Development Status :: 4 - Beta
Classifier: Intended Audience :: Developers
Classifier: Topic :: Software Development :: Localization
Classifier: Topic :: Software Development :: Internationalization
Classifier: License :: OSI Approved :: MIT License
Classifier: Programming Language :: Python :: 3
Classifier: Programming Language :: Python :: 3.6
Classifier: Programming Language :: Python :: 3.7
Classifier: Programming Language :: Python :: 3.8
Classifier: Programming Language :: Python :: 3.9
Classifier: Programming Language :: Python :: 3.10
Classifier: Programming Language :: Python :: 3.11
Classifier: Programming Language :: Python :: 3.12
Classifier: Operating System :: OS Independent
Classifier: Environment :: Console
Requires-Python: >=3.6
License-File: LICENSE
Dynamic: author
Dynamic: home-page
Dynamic: license-file
Dynamic: requires-python
